mopidy_sangu/__init__.py
mopidy_sangu/__version__.py
mopidy_sangu/ext.conf
mopidy_sangu/actor/__init__.py
mopidy_sangu/actor/fallback_music_actor.py
mopidy_sangu/api/__init__.py
mopidy_sangu/api/admin.py
mopidy_sangu/api/config.py
mopidy_sangu/api/unvote.py
mopidy_sangu/api/vote.py
mopidy_sangu/api/vote_data.py
mopidy_sangu/static/.last_build_id
mopidy_sangu/static/favicon.ico
mopidy_sangu/static/flutter_service_worker.js
mopidy_sangu/static/index.html
mopidy_sangu/static/main.dart.js
mopidy_sangu/static/manifest.json
mopidy_sangu/static/version.json
mopidy_sangu/static/assets/AssetManifest.json
mopidy_sangu/static/assets/FontManifest.json
mopidy_sangu/static/assets/NOTICES
mopidy_sangu/static/assets/fonts/MaterialIcons-Regular.otf
mopidy_sangu/static/assets/images/jellyfin.png
mopidy_sangu/static/assets/images/soundcloud.png
mopidy_sangu/static/assets/images/spotify.png
mopidy_sangu/static/assets/packages/cupertino_icons/assets/CupertinoIcons.ttf
mopidy_sangu/static/icons/Icon-192.png
mopidy_sangu/static/icons/Icon-512.png
mopidy_sangu/storage/__init__.py
mopidy_sangu/storage/storage.py
Mopidy_Sangu-1.2.0.dist-info/LICENSE
Mopidy_Sangu-1.2.0.dist-info/METADATA
Mopidy_Sangu-1.2.0.dist-info/WHEEL
Mopidy_Sangu-1.2.0.dist-info/entry_points.txt
Mopidy_Sangu-1.2.0.dist-info/top_level.txt
Mopidy_Sangu-1.2.0.dist-info/RECORD
